Workbook

Sheet Inputs
A1: Project | B1: Karatepe RES
A2: Capex (USD) | B2: 20000000
A3: Equity (USD) | B3: 6400000
A4: Total debt (USD) | B4: 13600000
A5: Local bank debt (USD) | B5: 13600000
A6: ECA debt (USD) | B6: 0
A7: Margin over base, current (%) | B7: 2.9
A8: Grace (months) | B8: 10
A9: Tenor initial (years) | B9: 13
A10: Tenor current (years) | B10: 13
A11: Financial close | B11: 44525
A12: DEMO_TODAY | B12: 46301
A13: Covenant DSCR initial | B13: 1.25
... A15: Covenant change effective | B15: 45731
A17: Year | B17: Base rate % (Term SOFR 6M, fictional)
A18: 2022 | B18: 2
A19: 2023 | B19: 4.8
A20: 2024 | B20: 5
A21: 2025 | B21: 4.3
A22: 2026 | B22: 3.6
A23: 2027 | B23: 3.2
A24: 2028 | B24: 3
A25: 2029 | B25: 3
A26: 2030 | B26: 3
A27: 2031 | B27: 3
A28: 2032 | B28: 3
A29: 2033 | B29: 3
... A31: 2035 | B31: 3
A33: Drawdown date | B33: Amount (USD)
A34: 44757 | B34: 8000000
A35: 44941 | B35: 5600000

Sheet Debt
A1: Period | B1: End date | C1: Opening (USD) | D1: Drawdown (USD) | E1: Principal (USD) | F1: All-in rate % | G1: Interest (USD) | H1: Closing (USD)
A2: H2_2022 | B2: 44926 | C2: 0 | D2: 8000000 | E2: 0 | F2: =VLOOKUP(YEAR(B2),Inputs!$A$18:$B$31,2,FALSE())+Inputs_Margin -> 4.9 | G2: =ROUND(C2*F2/100/2,2) -> 0 | H2: =C2+D2-E2 -> 8000000
A3: H1_2023 | B3: 45107 | C3: =H2 -> 8000000 | D3: 5600000 | E3: 172700 | F3: =VLOOKUP(YEAR(B3),Inputs!$A$18:$B$31,2,FALSE())+Inputs_Margin -> 7.7 | G3: =ROUND(C3*F3/100/2,2) -> 308000 | H3: =C3+D3-E3 -> 13427300
A4: H2_2023 | B4: 45291 | C4: =H3 -> 13427300 | D4: 0 | E4: 206900 | F4: =VLOOKUP(YEAR(B4),Inputs!$A$18:$B$31,2,FALSE())+Inputs_Margin -> 7.7 | G4: =ROUND(C4*F4/100/2,2) -> 516951.05 | H4: =C4+D4-E4 -> 13220400
A5: H1_2024 | B5: 45473 | C5: =H4 -> 13220400 | D5: 0 | E5: 241200 | F5: =VLOOKUP(YEAR(B5),Inputs!$A$18:$B$31,2,FALSE())+Inputs_Margin -> 7.9 | G5: =ROUND(C5*F5/100/2,2) -> 522205.8 | H5: =C5+D5-E5 -> 12979200
A6: H2_2024 | B6: 45657 | C6: =H5 -> 12979200 | D6: 0 | E6: 275500 | F6: =VLOOKUP(YEAR(B6),Inputs!$A$18:$B$31,2,FALSE())+Inputs_Margin -> 7.9 | G6: =ROUND(C6*F6/100/2,2) -> 512678.4 | H6: =C6+D6-E6 -> 12703700
A7: H1_2025 | B7: 45838 | C7: =H6 -> 12703700 | D7: 0 | E7: 309700 | F7: =VLOOKUP(YEAR(B7),Inputs!$A$18:$B$31,2,FALSE())+Inputs_Margin -> 7.2 | G7: =ROUND(C7*F7/100/2,2) -> 457333.2 | H7: =C7+D7-E7 -> 12394000
A8: H2_2025 | B8: 46022 | C8: =H7 -> 12394000 | D8: 0 | E8: 344000 | F8: =VLOOKUP(YEAR(B8),Inputs!$A$18:$B$31,2,FALSE())+Inputs_Margin -> 7.2 | G8: =ROUND(C8*F8/100/2,2) -> 446184 | H8: =C8+D8-E8 -> 12050000
A9: H1_2026 | B9: 46203 | C9: =H8 -> 12050000 | D9: 0 | E9: 378200 | F9: =VLOOKUP(YEAR(B9),Inputs!$A$18:$B$31,2,FALSE())+Inputs_Margin -> 6.5 | G9: =ROUND(C9*F9/100/2,2) -> 391625 | H9: =C9+D9-E9 -> 11671800
A10: H2_2026 | B10: 46387 | C10: =H9 -> 11671800 | D10: 0 | E10: 412500 | F10: =VLOOKUP(YEAR(B10),Inputs!$A$18:$B$31,2,FALSE())+Inputs_Margin -> 6.5 | G10: =ROUND(C10*F10/100/2,2) -> 379333.5 | H10: =C10+D10-E10 -> 11259300
A11: H1_2027 | B11: 46568 | C11: =H10 -> 11259300 | D11: 0 | E11: 446800 | F11: =VLOOKUP(YEAR(B11),Inputs!$A$18:$B$31,2,FALSE())+Inputs_Margin -> 6.1 | G11: =ROUND(C11*F11/100/2,2) -> 343408.65 | H11: =C11+D11-E11 -> 10812500
A12: H2_2027 | B12: 46752 | C12: =H11 -> 10812500 | D12: 0 | E12: 481000 | F12: =VLOOKUP(YEAR(B12),Inputs!$A$18:$B$31,2,FALSE())+Inputs_Margin -> 6.1 | G12: =ROUND(C12*F12/100/2,2) -> 329781.25 | H12: =C12+D12-E12 -> 10331500
A13: H1_2028 | B13: 46934 | C13: =H12 -> 10331500 | D13: 0 | E13: 515300 | F13: =VLOOKUP(YEAR(B13),Inputs!$A$18:$B$31,2,FALSE())+Inputs_Margin -> 5.9 | G13: =ROUND(C13*F13/100/2,2) -> 304779.25 | H13: =C13+D13-E13 -> 9816200
A14: H2_2028 | B14: 47118 | C14: =H13 -> 9816200 | D14: 0 | E14: 549500 | F14: =VLOOKUP(YEAR(B14),Inputs!$A$18:$B$31,2,FALSE())+Inputs_Margin -> 5.9 | G14: =ROUND(C14*F14/100/2,2) -> 289577.9 | H14: =C14+D14-E14 -> 9266700
... A26: H2_2034 | B26: 49309 | C26: =H25 -> 960600 | D26: 0 | E26: 960600 | F26: =VLOOKUP(YEAR(B26),Inputs!$A$18:$B$31,2,FALSE())+Inputs_Margin -> 5.9 | G26: =ROUND(C26*F26/100/2,2) -> 28337.7 | H26: =C26+D26-E26 -> 0

Sheet DSCR
A1: Quarter | B1: Quarter end | C1: Half | D1: CFADS (USD) | E1: Debt service (USD) | F1: DSCR | G1: Covenant | H1: Result
A2: Q4_2023 | B2: 45291 | C2: H2_2023 | D2: 513900 | E2: =(INDEX(Debt!$E$2:$E$26,MATCH(C2,Debt!$A$2:$A$26,0))+INDEX(Debt!$G$2:$G$26,MATCH(C2,Debt!$A$2:$A$26,0)))/2 -> 361925.53 | F2: =ROUND(D2/E2,2) -> 1.42 | G2: =IF(B2>=Inputs!$B$15,Inputs!$B$14,Inputs!$B$13) -> 1.25 | H2: =IF(F2>=G2,"pass","fail") -> pass
A3: Q1_2024 | B3: 45382 | C3: H1_2024 | D3: 526800 | E3: =(INDEX(Debt!$E$2:$E$26,MATCH(C3,Debt!$A$2:$A$26,0))+INDEX(Debt!$G$2:$G$26,MATCH(C3,Debt!$A$2:$A$26,0)))/2 -> 381702.9 | F3: =ROUND(D3/E3,2) -> 1.38 | G3: =IF(B3>=Inputs!$B$15,Inputs!$B$14,Inputs!$B$13) -> 1.25 | H3: =IF(F3>=G3,"pass","fail") -> pass
A4: Q2_2024 | B4: 45473 | C4: H1_2024 | D4: 500000 | E4: =(INDEX(Debt!$E$2:$E$26,MATCH(C4,Debt!$A$2:$A$26,0))+INDEX(Debt!$G$2:$G$26,MATCH(C4,Debt!$A$2:$A$26,0)))/2 -> 381702.9 | F4: =ROUND(D4/E4,2) -> 1.31 | G4: =IF(B4>=Inputs!$B$15,Inputs!$B$14,Inputs!$B$13) -> 1.25 | H4: =IF(F4>=G4,"pass","fail") -> pass
A5: Q3_2024 | B5: 45565 | C5: H2_2024 | D5: 500500 | E5: =(INDEX(Debt!$E$2:$E$26,MATCH(C5,Debt!$A$2:$A$26,0))+INDEX(Debt!$G$2:$G$26,MATCH(C5,Debt!$A$2:$A$26,0)))/2 -> 394089.2 | F5: =ROUND(D5/E5,2) -> 1.27 | G5: =IF(B5>=Inputs!$B$15,Inputs!$B$14,Inputs!$B$13) -> 1.25 | H5: =IF(F5>=G5,"pass","fail") -> pass
A6: Q4_2024 | B6: 45657 | C6: H2_2024 | D6: 488700 | E6: =(INDEX(Debt!$E$2:$E$26,MATCH(C6,Debt!$A$2:$A$26,0))+INDEX(Debt!$G$2:$G$26,MATCH(C6,Debt!$A$2:$A$26,0)))/2 -> 394089.2 | F6: =ROUND(D6/E6,2) -> 1.24 | G6: =IF(B6>=Inputs!$B$15,Inputs!$B$14,Inputs!$B$13) -> 1.25 | H6: =IF(F6>=G6,"pass","fail") -> fail
A7: Q1_2025 | B7: 45747 | C7: H1_2025 | D7: 471700 | E7: =(INDEX(Debt!$E$2:$E$26,MATCH(C7,Debt!$A$2:$A$26,0))+INDEX(Debt!$G$2:$G$26,MATCH(C7,Debt!$A$2:$A$26,0)))/2 -> 383516.6 | F7: =ROUND(D7/E7,2) -> 1.23 | G7: =IF(B7>=Inputs!$B$15,Inputs!$B$14,Inputs!$B$13) -> 1.2 | H7: =IF(F7>=G7,"pass","fail") -> pass
A8: Q2_2025 | B8: 45838 | C8: H1_2025 | D8: 494700 | E8: =(INDEX(Debt!$E$2:$E$26,MATCH(C8,Debt!$A$2:$A$26,0))+INDEX(Debt!$G$2:$G$26,MATCH(C8,Debt!$A$2:$A$26,0)))/2 -> 383516.6 | F8: =ROUND(D8/E8,2) -> 1.29 | G8: =IF(B8>=Inputs!$B$15,Inputs!$B$14,Inputs!$B$13) -> 1.2 | H8: =IF(F8>=G8,"pass","fail") -> pass
A9: Q3_2025 | B9: 45930 | C9: H2_2025 | D9: 525500 | E9: =(INDEX(Debt!$E$2:$E$26,MATCH(C9,Debt!$A$2:$A$26,0))+INDEX(Debt!$G$2:$G$26,MATCH(C9,Debt!$A$2:$A$26,0)))/2 -> 395092 | F9: =ROUND(D9/E9,2) -> 1.33 | G9: =IF(B9>=Inputs!$B$15,Inputs!$B$14,Inputs!$B$13) -> 1.2 | H9: =IF(F9>=G9,"pass","fail") -> pass
A10: Q4_2025 | B10: 46022 | C10: H2_2025 | D10: 537300 | E10: =(INDEX(Debt!$E$2:$E$26,MATCH(C10,Debt!$A$2:$A$26,0))+INDEX(Debt!$G$2:$G$26,MATCH(C10,Debt!$A$2:$A$26,0)))/2 -> 395092 | F10: =ROUND(D10/E10,2) -> 1.36 | G10: =IF(B10>=Inputs!$B$15,Inputs!$B$14,Inputs!$B$13) -> 1.2 | H10: =IF(F10>=G10,"pass","fail") -> pass
A11: Q1_2026 | B11: 46112 | C11: H1_2026 | D11: 515800 | E11: =(INDEX(Debt!$E$2:$E$26,MATCH(C11,Debt!$A$2:$A$26,0))+INDEX(Debt!$G$2:$G$26,MATCH(C11,Debt!$A$2:$A$26,0)))/2 -> 384912.5 | F11: =ROUND(D11/E11,2) -> 1.34 | G11: =IF(B11>=Inputs!$B$15,Inputs!$B$14,Inputs!$B$13) -> 1.2 | H11: =IF(F11>=G11,"pass","fail") -> pass
A12: Q2_2026 | B12: 46203 | C12: H1_2026 | D12: 527300 | E12: =(INDEX(Debt!$E$2:$E$26,MATCH(C12,Debt!$A$2:$A$26,0))+INDEX(Debt!$G$2:$G$26,MATCH(C12,Debt!$A$2:$A$26,0)))/2 -> 384912.5 | F12: =ROUND(D12/E12,2) -> 1.37 | G12: =IF(B12>=Inputs!$B$15,Inputs!$B$14,Inputs!$B$13) -> 1.2 | H12: =IF(F12>=G12,"pass","fail") -> pass

Sheet Cashflow
A1: Quarter | B1: CFADS (USD) | C1: Debt service (USD) | D1: Cash to equity (USD) | E1: Cumulative (USD)
A2: Q4_2023 | B2: =DSCR!D2 -> 513900 | C2: =DSCR!E2 -> 361925.53 | D2: =B2-C2 -> 151974.48 | E2: =D2 -> 151974.48
A3: Q1_2024 | B3: =DSCR!D3 -> 526800 | C3: =DSCR!E3 -> 381702.9 | D3: =B3-C3 -> 145097.1 | E3: =E2+D3 -> 297071.58
A4: Q2_2024 | B4: =DSCR!D4 -> 500000 | C4: =DSCR!E4 -> 381702.9 | D4: =B4-C4 -> 118297.1 | E4: =E3+D4 -> 415368.67
A5: Q3_2024 | B5: =DSCR!D5 -> 500500 | C5: =DSCR!E5 -> 394089.2 | D5: =B5-C5 -> 106410.8 | E5: =E4+D5 -> 521779.47
A6: Q4_2024 | B6: =DSCR!D6 -> 488700 | C6: =DSCR!E6 -> 394089.2 | D6: =B6-C6 -> 94610.8 | E6: =E5+D6 -> 616390.28
A7: Q1_2025 | B7: =DSCR!D7 -> 471700 | C7: =DSCR!E7 -> 383516.6 | D7: =B7-C7 -> 88183.4 | E7: =E6+D7 -> 704573.68
A8: Q2_2025 | B8: =DSCR!D8 -> 494700 | C8: =DSCR!E8 -> 383516.6 | D8: =B8-C8 -> 111183.4 | E8: =E7+D8 -> 815757.07
A9: Q3_2025 | B9: =DSCR!D9 -> 525500 | C9: =DSCR!E9 -> 395092 | D9: =B9-C9 -> 130408 | E9: =E8+D9 -> 946165.07
A10: Q4_2025 | B10: =DSCR!D10 -> 537300 | C10: =DSCR!E10 -> 395092 | D10: =B10-C10 -> 142208 | E10: =E9+D10 -> 1088373.1
A11: Q1_2026 | B11: =DSCR!D11 -> 515800 | C11: =DSCR!E11 -> 384912.5 | D11: =B11-C11 -> 130887.5 | E11: =E10+D11 -> 1219260.6
A12: Q2_2026 | B12: =DSCR!D12 -> 527300 | C12: =DSCR!E12 -> 384912.5 | D12: =B12-C12 -> 142387.5 | E12: =E11+D12 -> 1361648.1

Sheet _meta
A1: DEMO — synthetic demo workbook (Company AI V0); figures are fictional
A2: generated_at | B2: 2026-10-10T19:37:43+00:00
A3: ledger_schema_version | B3: 1
A4: demo_today | B4: 2026-10-06
